kspec_gfa_controller/__init__.py
kspec_gfa_controller/main.py
kspec_gfa_controller/save/2024-08-09 16:17:22grab_cam_40074358.fits
kspec_gfa_controller/save/2024-08-09 16:17:22grab_cam_40074358.png
kspec_gfa_controller/save/2024-08-09 16:17:22grab_cam_40103834.fits
kspec_gfa_controller/save/2024-08-09 16:17:22grab_cam_40103834.png
kspec_gfa_controller/save/2024-08-09 16:17:23grab_cam_40103663.fits
kspec_gfa_controller/save/2024-08-09 16:17:23grab_cam_40103663.png
kspec_gfa_controller/save/2024-08-09 16:17:24grab_cam_40103833.fits
kspec_gfa_controller/save/2024-08-09 16:17:24grab_cam_40103833.png
kspec_gfa_controller/save/2024-08-09 16:18:24_grab_cam_40074358.fits
kspec_gfa_controller/save/2024-08-09 16:18:24_grab_cam_40074358.png
kspec_gfa_controller/save/2024-08-09 16:18:24_grab_cam_40103834.fits
kspec_gfa_controller/save/2024-08-09 16:18:24_grab_cam_40103834.png
kspec_gfa_controller/save/2024-08-09 16:18:25_grab_cam_40103663.fits
kspec_gfa_controller/save/2024-08-09 16:18:25_grab_cam_40103663.png
kspec_gfa_controller/save/2024-08-09 16:18:26_grab_cam_40103833.fits
kspec_gfa_controller/save/2024-08-09 16:18:26_grab_cam_40103833.png
kspec_gfa_controller/save/2024-08-09 16:19:20_grab_cam_40103663.fits
kspec_gfa_controller/save/2024-08-09 16:19:20_grab_cam_40103663.png
kspec_gfa_controller/save/2024-08-09 16:19:21_grab_cam_40103833.fits
kspec_gfa_controller/save/2024-08-09 16:19:21_grab_cam_40103833.png
kspec_gfa_controller/save/2024-08-09 16:19:48_grab_cam_40103663.fits
kspec_gfa_controller/save/2024-08-09 16:19:48_grab_cam_40103663.png
kspec_gfa_controller/save/2024-08-09 16:19:48_grab_cam_40103834.fits
kspec_gfa_controller/save/2024-08-09 16:19:48_grab_cam_40103834.png
kspec_gfa_controller/save/2024-08-09 16:19:49_grab_cam_40103833.fits
kspec_gfa_controller/save/2024-08-09 16:19:49_grab_cam_40103833.png
kspec_gfa_controller/save/2024-08-09 16:20:07_grab_cam_40103834.fits
kspec_gfa_controller/save/2024-08-09 16:20:07_grab_cam_40103834.png
kspec_gfa_controller-0.6.0.dist-info/METADATA
kspec_gfa_controller-0.6.0.dist-info/WHEEL
kspec_gfa_controller-0.6.0.dist-info/RECORD
