Metadata-Version: 2.1
Name: kspec-gfa-controller
Version: 0.6.0
Summary: The Controller software for KSPEC-GFA Camera
Author: Mingyeong Yang
Author-email: mmingyeong@kasi.re.kr
Requires-Python: >=3.10,<4.0
Classifier: Programming Language :: Python :: 3
Classifier: Programming Language :: Python :: 3.10
Classifier: Programming Language :: Python :: 3.11
Classifier: Programming Language :: Python :: 3.12
Requires-Dist: astropy (>=6.1.2,<7.0.0)
Requires-Dist: asyncio (>=3.4.3,<4.0.0)
Requires-Dist: datetime (>=5.5,<6.0)
Requires-Dist: logging (>=0.4.9.6,<0.5.0.0)
Requires-Dist: pypylon (>=4.0.0,<5.0.0)
